{"name":"sentient_car","spriteSheetImage":"sentient_car.png","spriteWidth":128,"spriteHeight":128,"leftBuffer":0,"rightBuffer":0,"topBuffer":0,"bottomBuffer":0,"columns":8,"rows":6,"animations":[{"name":"IDLE","repeat":true,"frames":[{"index":0,"duration":2},{"index":1,"duration":2},{"index":2,"duration":2},{"index":3,"duration":2},{"index":4,"duration":2}]},{"name":"IDLE_LEFT","repeat":true,"frames":[{"index":12,"duration":2},{"index":13,"duration":2},{"index":14,"duration":2},{"index":15,"duration":2},{"index":16,"duration":2},{"index":17,"duration":2},{"index":18,"duration":2}]},{"name":"MOVING_LEFT","repeat":true,"frames":[{"index":19,"duration":2},{"index":20,"duration":2},{"index":21,"duration":2},{"index":22,"duration":2},{"index":23,"duration":2},{"index":24,"duration":2}]},{"name":"IDLE_BACK","repeat":true,"frames":[{"index":6,"duration":2},{"index":7,"duration":2},{"index":8,"duration":2},{"index":9,"duration":2},{"index":10,"duration":2},{"index":11,"duration":2}]},{"name":"MOVING_UP","repeat":true,"frames":[{"index":25,"duration":2},{"index":26,"duration":2},{"index":27,"duration":2},{"index":28,"duration":2},{"index":29,"duration":2},{"index":30,"duration":2}]},{"name":"WRECK","repeat":true,"frames":[{"index":31,"duration":2},{"index":32,"duration":2},{"index":33,"duration":2},{"index":34,"duration":2},{"index":35,"duration":2},{"index":36,"duration":2},{"index":37,"duration":2},{"index":38,"duration":2},{"index":39,"duration":2},{"index":40,"duration":2}]}]}